{
    "About": "SOBRE",
    "ClientUpgradeTitle": "Atualiza\u00e7\u00e3o dispon\u00edvel",
    "DLCIndicatorProgress": "{0} de {1} MB conclu\u00eddos.",
    "DLCProgress": "Baixando atualiza\u00e7\u00f5es {0} de {1} MB conclu\u00eddo.",
    "DLCProgressTitle": "Baixando",
    "Description": "DESCRI\u00c7\u00c3O",
    "DuplicateLogin": "Detec\u00e7\u00e3o De Login Duplicado",
    "DuplicateLoginDetail": "Este jogo est\u00e1 sendo jogado em outro aparelho.",
    "FatalMessage": "Por favor, reinicie o jogo.",
    "FatalNetworkMessage": "Verifique o status da rede e reinicie o jogo.",
    "FatalNetworkTitle": "Rede Indispon\u00edvel",
    "FatalTitle": "Algo deu errado.",
    "ForcedClientUpgradeMessage": "Uma nova vers\u00e3o do Minions Paradise est\u00e1 dispon\u00edvel. Por favor, atualize para continuar.",
    "InsufficientLevel": "Desbloqueia no n\u00edvel {0}",
    "InsufficientStorage": "Espa\u00e7o insuficiente",
    "InsufficientStorageMessage": "O Minions Paradise necessita de pelo menos {0} megabytes de espa\u00e7o livre adicional.",
    "NoInternetConnection": "Para usar este recurso, voc\u00ea precisa estar online. Por favor, certifique-se que voc\u00ea est\u00e1 conectado \u00e0 internet e tente novamente.",
    "NoWiFiContinue": "CONTINUAR",
    "NoWiFiExit": "SAIR",
    "NoWiFiHeading": "SEM WI-FI",
    "NoWiFiMessage": "Voc\u00ea n\u00e3o est\u00e1 conectado a uma rede Wi-Fi. \u00c9 recomendado que voc\u00ea se conecte a uma rede Wi-Fi para n\u00e3o incorrer em cobran\u00e7as de dados significativas ao fazer downloads com a sua rede de celular.",
    "NoWiFiSettings": "CONFIGURA\u00c7\u00d5ES",
    "NudgeClientUpgradeMessage": "Uma nova vers\u00e3o do Minions Paradise est\u00e1 dispon\u00edvel.",
    "OfflineDescription": "Nenhuma rede encontrada.\nPor favor, conecte-se a uma rede Wi-Fi ou rede de dados celulares.",
    "OfflineRetry": "TENTAR DE NOVO",
    "OfflineTitle": "N\u00c3O FOI POSS\u00cdVEL SE CONECTAR AO SERVIDOR",
    "StarterPackAlt": "Esse \u00e9 um Pacote de Iniciante",
    "Update": "Atualiza\u00e7\u00e3o",
    "defaultTip001": "Pegando ondas...",
    "defaultTip002": "Espalhando areia...",
    "defaultTip003": "Descascando bananas...",
    "defaultTip004": "Quebrando cocos...",
    "defaultTip005": "Invadindo festas...",
    "defaultTip006": "Festejando muito...",
    "defaultTip007": "Pulando pelas ilhas...",
    "defaultTip008": "Enfeitando bebidas...",
    "defaultTip009": "Bronzeando bumbuns...",
    "defaultTip010": "Afofando toalhas...",
    "defaultTip011": "Deixando brindes..."
}